ifexd/__init__.py
ifexd/haarcascade_eye.xml
ifexd/haarcascade_frontalface_default.xml
ifexd-0.0.0.dist-info/LICENSE
ifexd-0.0.0.dist-info/METADATA
ifexd-0.0.0.dist-info/WHEEL
ifexd-0.0.0.dist-info/top_level.txt
ifexd-0.0.0.dist-info/RECORD
