Metadata-Version: 2.1
Name: ifexd
Version: 0.0.0
Summary: IFExD: Indian Facial Expression Dataset
Home-page: https://github.com/Nikeshbajaj/ifexd
Author: Nikesh Bajaj
Author-email: nikkeshbajaj@gmail.com
License: MIT
Keywords: Facial-Expression-Dataset Computer-Vision CNN
Platform: UNKNOWN
Classifier: Programming Language :: Python :: 3
Classifier: License :: OSI Approved :: MIT License
Classifier: Operating System :: OS Independent
Requires-Dist: numpy
Requires-Dist: matplotlib
Requires-Dist: spkit
